incentive_v1/__init__.py
incentive_v1/admin.py
incentive_v1/apps.py
incentive_v1/models.py
incentive_v1/tests.py
incentive_v1/views.py
incentive_v1-0.1.dist-info/LICENSE
incentive_v1-0.1.dist-info/METADATA
incentive_v1-0.1.dist-info/WHEEL
incentive_v1-0.1.dist-info/top_level.txt
incentive_v1-0.1.dist-info/RECORD
